<?xml version="1.0" encoding="UTF-8"?>
<Pista NombreDeLaPista="Default" LargoDeLaPista="1200" AnchoDeLaPista="6">
  <ListaDePozos CantidadDePozos="50">
    <Pozo posicionX="1" posicionY="12" />
    <Pozo posicionX="2" posicionY="24" />
    <Pozo posicionX="3" posicionY="36" />
    <Pozo posicionX="4" posicionY="48" />
    <Pozo posicionX="5" posicionY="60" />
    <Pozo posicionX="6" posicionY="72" />
    <Pozo posicionX="1" posicionY="84" />
    <Pozo posicionX="2" posicionY="96" />
    <Pozo posicionX="3" posicionY="108" />
    <Pozo posicionX="4" posicionY="120" />
    <Pozo posicionX="5" posicionY="132" />
    <Pozo posicionX="6" posicionY="144" />
    <Pozo posicionX="1" posicionY="156" />
    <Pozo posicionX="2" posicionY="168" />
    <Pozo posicionX="3" posicionY="180" />
    <Pozo posicionX="4" posicionY="192" />
    <Pozo posicionX="5" posicionY="2040" />
    <Pozo posicionX="6" posicionY="216" />
    <Pozo posicionX="1" posicionY="228" />
    <Pozo posicionX="2" posicionY="240" />
    <Pozo posicionX="3" posicionY="252" />
    <Pozo posicionX="4" posicionY="264" />
    <Pozo posicionX="5" posicionY="276" />
    <Pozo posicionX="6" posicionY="288" />
    <Pozo posicionX="1" posicionY="300" />
    <Pozo posicionX="2" posicionY="312" />
    <Pozo posicionX="3" posicionY="324" />
    <Pozo posicionX="4" posicionY="336" />
    <Pozo posicionX="5" posicionY="348" />
    <Pozo posicionX="6" posicionY="360" />
    <Pozo posicionX="1" posicionY="372" />
    <Pozo posicionX="2" posicionY="384" />
    <Pozo posicionX="3" posicionY="396" />
    <Pozo posicionX="4" posicionY="408" />
    <Pozo posicionX="5" posicionY="420" />
    <Pozo posicionX="6" posicionY="432" />
    <Pozo posicionX="1" posicionY="444" />
    <Pozo posicionX="2" posicionY="456" />
    <Pozo posicionX="3" posicionY="468" />
    <Pozo posicionX="4" posicionY="480" />
    <Pozo posicionX="5" posicionY="492" />
    <Pozo posicionX="6" posicionY="504" />
    <Pozo posicionX="1" posicionY="516" />
    <Pozo posicionX="2" posicionY="528" />
    <Pozo posicionX="3" posicionY="540" />
    <Pozo posicionX="4" posicionY="552" />
    <Pozo posicionX="5" posicionY="564" />
    <Pozo posicionX="6" posicionY="576" />
    <Pozo posicionX="1" posicionY="588" />
    <Pozo posicionX="2" posicionY="600" />
  </ListaDePozos>
  <ListaDeLomasDeBurro CantidadDeLomasDeBurro="60">
    <LomaDeBurro posicionX="1" posicionY="30" />
    <LomaDeBurro posicionX="1" posicionY="40" />
    <LomaDeBurro posicionX="1" posicionY="50" />
    <LomaDeBurro posicionX="1" posicionY="60" />
    <LomaDeBurro posicionX="1" posicionY="70" />
    <LomaDeBurro posicionX="1" posicionY="80" />
    <LomaDeBurro posicionX="1" posicionY="90" />
    <LomaDeBurro posicionX="1" posicionY="100" />
    <LomaDeBurro posicionX="1" posicionY="110" />
    <LomaDeBurro posicionX="1" posicionY="120" />
    <LomaDeBurro posicionX="1" posicionY="130" />
    <LomaDeBurro posicionX="1" posicionY="140" />
    <LomaDeBurro posicionX="1" posicionY="150" />
    <LomaDeBurro posicionX="1" posicionY="160" />
    <LomaDeBurro posicionX="1" posicionY="170" />
    <LomaDeBurro posicionX="1" posicionY="180" />
    <LomaDeBurro posicionX="1" posicionY="190" />
    <LomaDeBurro posicionX="1" posicionY="200" />
    <LomaDeBurro posicionX="1" posicionY="210" />
    <LomaDeBurro posicionX="1" posicionY="220" />
    <LomaDeBurro posicionX="1" posicionY="230" />
    <LomaDeBurro posicionX="1" posicionY="240" />
    <LomaDeBurro posicionX="1" posicionY="250" />
    <LomaDeBurro posicionX="1" posicionY="260" />
    <LomaDeBurro posicionX="1" posicionY="270" />
    <LomaDeBurro posicionX="1" posicionY="280" />
    <LomaDeBurro posicionX="1" posicionY="290" />
    <LomaDeBurro posicionX="1" posicionY="300" />
    <LomaDeBurro posicionX="1" posicionY="310" />
    <LomaDeBurro posicionX="1" posicionY="320" />
    <LomaDeBurro posicionX="1" posicionY="330" />
    <LomaDeBurro posicionX="1" posicionY="340" />
    <LomaDeBurro posicionX="1" posicionY="350" />
    <LomaDeBurro posicionX="1" posicionY="360" />
    <LomaDeBurro posicionX="1" posicionY="370" />
    <LomaDeBurro posicionX="1" posicionY="380" />
    <LomaDeBurro posicionX="1" posicionY="390" />
    <LomaDeBurro posicionX="1" posicionY="400" />
    <LomaDeBurro posicionX="1" posicionY="410" />
    <LomaDeBurro posicionX="1" posicionY="420" />
    <LomaDeBurro posicionX="1" posicionY="430" />
    <LomaDeBurro posicionX="1" posicionY="440" />
    <LomaDeBurro posicionX="1" posicionY="450" />
    <LomaDeBurro posicionX="1" posicionY="460" />
    <LomaDeBurro posicionX="1" posicionY="470" />
    <LomaDeBurro posicionX="1" posicionY="480" />
    <LomaDeBurro posicionX="1" posicionY="490" />
    <LomaDeBurro posicionX="1" posicionY="500" />
    <LomaDeBurro posicionX="1" posicionY="510" />
    <LomaDeBurro posicionX="1" posicionY="520" />
    <LomaDeBurro posicionX="1" posicionY="530" />
    <LomaDeBurro posicionX="1" posicionY="540" />
    <LomaDeBurro posicionX="1" posicionY="550" />
    <LomaDeBurro posicionX="1" posicionY="560" />
    <LomaDeBurro posicionX="1" posicionY="570" />
    <LomaDeBurro posicionX="1" posicionY="580" />
    <LomaDeBurro posicionX="1" posicionY="590" />
    <LomaDeBurro posicionX="1" posicionY="600" />
    <LomaDeBurro posicionX="1" posicionY="610" />
    <LomaDeBurro posicionX="1" posicionY="620" />
  </ListaDeLomasDeBurro>
  <ListaDeTerrenos CantidadDeTerrenos="3">
    <Asfalto principio="0" fin="500" />
    <Tierra principio="501" fin="800" />
    <Ripio principio="801" fin="1200" />
  </ListaDeTerrenos>
  <ListaDeMejoresTiempos>
    <Tiempo Nombre="Seba" Tiempo="23.0" />
    <Tiempo Nombre="Seba" Tiempo="29.0" />
    <Tiempo Nombre="Jugador1" Tiempo="370.0" />
    <Tiempo Nombre="Vacio" Tiempo="0.0" />
    <Tiempo Nombre="Vacio" Tiempo="0.0" />
    <Tiempo Nombre="Vacio" Tiempo="0.0" />
    <Tiempo Nombre="Vacio" Tiempo="0.0" />
    <Tiempo Nombre="Vacio" Tiempo="0.0" />
    <Tiempo Nombre="Vacio" Tiempo="0.0" />
    <Tiempo Nombre="Vacio" Tiempo="0.0" />
  </ListaDeMejoresTiempos>
</Pista>

